TradeCalCN/__init__.py
TradeCalCN/calendar_test.py
TradeCalCN-0.1.1.dist-info/METADATA
TradeCalCN-0.1.1.dist-info/WHEEL
TradeCalCN-0.1.1.dist-info/top_level.txt
TradeCalCN-0.1.1.dist-info/RECORD
