Metadata-Version: 2.1
Name: TradeCalCN
Version: 0.1.1
Requires-Dist: baostock
Requires-Dist: Pandas
